{
    "categories": [
        {
            "name": "Kişiye Özel Beslenme Danışmanlığı",
            "subcategory": [
                "1",
                "2",
                "3"
            ]
        },
        {
            "name": "Kilo Verme Programı",
            "subcategory": [
                "1",
                "2",
                "3"
            ]
        },
        {
            "name": "Kilo Alma Programı",
            "subcategory": [
                "1",
                "2",
                "3"
            ]
        },
        {
            "name": "Kilo Koruma Programı",
            "subcategory": [
                "1",
                "2",
                "3"
            ]
        },
        {
            "name": "Fonksiyonel Tıp Diyetisyenliği",
            "subcategory": [
                "1",
                "2",
                "3"
            ]
        },
        {
            "name": "Kurumsal Beslenme Danışmanlığı",
            "subcategory": [
                "1",
                "2",
                "3"
            ]
        },
        {
            "name": "Menü Planlama",
            "subcategory": [
                "1",
                "2",
                "3"
            ]
        },
        {
            "name": "Çocukluk Döneminde Beslenme",
            "subcategory": [
                "1",
                "2",
                "3"
            ]
        },
        {
            "name": "Ergenlikte Beslenm",
            "subcategory": [
                "1",
                "2",
                "3"
            ]
        },
        {
            "name": "Hastalıklarda Beslenme",
            "subcategory": [
                "1",
                "2",
                "3"
            ]
        },
        {
            "name": "Hamilelik Döneminde Beslenme",
            "subcategory": [
                "1",
                "2",
                "3"
            ]
        },
        {
            "name": "Emzirme Döneminde Beslenme",
            "subcategory": [
                "1",
                "2",
                "3"
            ]
        },
        {
            "name": "Menopoz Döneminde Beslenme",
            "subcategory": [
                "1",
                "2",
                "3"
            ]
        },
        {
            "name": "Yaşlılarda Beslenme",
            "subcategory": [
                "1",
                "2",
                "3"
            ]
        }
    ]
}